domepy/__init__.py
domepy/async_api/__init__.py
domepy/async_api/client.py
domepy/async_api/polymarket.py
domepy/core/__init__.py
domepy/core/schema.py
domepy/sync_api/__init__.py
domepy/sync_api/client.py
domepy/sync_api/polymarket.py
domepy-0.1.0.dist-info/METADATA
domepy-0.1.0.dist-info/WHEEL
domepy-0.1.0.dist-info/top_level.txt
domepy-0.1.0.dist-info/RECORD
